Metadata-Version: 1.0
Name: security-utils
Version: 0.0.2
Summary: Security utils
Home-page: UNKNOWN
Author: Alex Demure
Author-email: alexanderdemure@gmail.com
License: MIT
Keywords: itsdangerous
Platform: UNKNOWN
